{
	"OvGames": {
		"user_login": "OvGames",
		"user_id": 306144,
		"user_role": "DEV",
		"user_profile": {
			"channel_id": 169378,
			"user_login": "OvGames"
		},
		"badges": [
			{
				"title": "BetterWASD Разработчик",
				"html": "<div ovg='' class='badge_div' style='background-color: {user_color};'><i badge='' class='icon wasd-icons-dev dev'></i></div>",
				"tooltip": "<div ovg='' class='badge_div' style='background-color: {user_color};height: 20px;width: 23px;'><i badge='' class='icon wasd-icons-dev dev' style='position: relative;top: 2px;'></i></div>"
			}
		]
	}
}